optivolution/__init__.py
optivolution/chromosome.py
optivolution/population.py
OptivolutionPy-1.0.1.dist-info/LICENSE
OptivolutionPy-1.0.1.dist-info/METADATA
OptivolutionPy-1.0.1.dist-info/WHEEL
OptivolutionPy-1.0.1.dist-info/top_level.txt
OptivolutionPy-1.0.1.dist-info/RECORD
